LICENSE.txt
MANIFEST.in
README.rst
setup.py
piano_fingering/__init__.py
piano_fingering/cost.py
piano_fingering/fingering.py
piano_fingering/midi.py
piano_fingering.egg-info/PKG-INFO
piano_fingering.egg-info/SOURCES.txt
piano_fingering.egg-info/dependency_links.txt
piano_fingering.egg-info/top_level.txt
piano_fingering/test/__init__.py
piano_fingering/test/test_cost.py
piano_fingering/test/test_fingering.py
piano_fingering/test/test_midi.py