Metadata-Version: 1.1
Name: piano-fingering
Version: 1.0.0
Summary: Automatic fingering for notes played on piano
Home-page: https://github.com/Kanma/piano_fingering
Author: Philip Abbet
Author-email: philip.abbet@gmail.com
License: MIT
Download-URL: https://github.com/Kanma/piano_fingering/archive/v1.0.0.tar.gz
Keywords: piano,music
Platform: UNKNOWN
Classifier: Development Status :: 3 - Alpha
Classifier: License :: OSI Approved :: MIT License
Classifier: Programming Language :: Python :: 2.7
Classifier: Programming Language :: Python :: 3.6
Classifier: Topic :: Multimedia
Classifier: Intended Audience :: Developers
